ia256utilities/__init__.py
ia256utilities/filesystem.py
ia256utilities/hashfile.py
ia256utilities/win.py
ia256utilities-0.4.2.dist-info/LICENSE
ia256utilities-0.4.2.dist-info/METADATA
ia256utilities-0.4.2.dist-info/WHEEL
ia256utilities-0.4.2.dist-info/top_level.txt
ia256utilities-0.4.2.dist-info/RECORD
