Metadata-Version: 2.1
Name: ia256utilities
Version: 0.4.2
Summary: A set of useful utilities
Home-page: https://github.com/IceArrow256/ia256utilities
Author: IceArrow256
Author-email: icearrow256@gmail.com
License: The Unlicense
Platform: UNKNOWN
